{
  "jobs": [
    {
      "title": "Android App Developer",
      "type": "Remote",
      "salary": "500000",
      "deadline": "2026-06-30",
      "id": 2
    },
    {
      "title": "Product Manager",
      "type": "Remote",
      "salary": "18000",
      "deadline": "2023-12-31",
      "id": 4
    },
    {
      "title": "Social Media Manager",
      "type": "Internship",
      "salary": "20000",
      "deadline": "2023-11-30",
      "id": 5
    },
    {
      "title": "Frontend Developer",
      "type": "Full Time",
      "salary": "35000",
      "deadline": "2023-12-31",
      "id": 6
    },
    {
      "title": "Full Stack Developer",
      "type": "Internship",
      "salary": "18000",
      "deadline": "2023-12-31",
      "id": 7
    },
    {
      "title": "IOS App Developer",
      "type": "Full Time",
      "salary": "70000",
      "deadline": "2023-05-04",
      "id": 8
    }
  ]
}